hdl/keys_4x4.v
module keys_4x4(
    input wire clk,                // Clock do sistema
    input wire rst,                // Reset síncrono
    input wire [3:0] in,           // Entrada da tecla (linha/coluna)
    output reg [3:0] out,          // Valor decodificado da tecla
    output reg valid,              // Indica se a tecla foi validada
    output reg [15:0] press_duration // Duração da tecla pressionada
);

    reg [3:0] in_prev;
    reg [15:0] debounce_counter;
    reg [15:0] duration_counter;

    // reduzido para simulação (antes era 250000)
    parameter DEBOUNCE_LIMIT = 18'd10;

    always @(posedge clk) begin
        if (rst) begin
            out <= 4'h0;
            valid <= 1'b0;
            debounce_counter <= 16'd0;
            duration_counter <= 16'd0;
            press_duration <= 16'd0;
            in_prev <= 4'hF;
        end else begin
            if (in == in_prev) begin
                // Incrementa contador de debounce
                if (debounce_counter < DEBOUNCE_LIMIT) begin
                    debounce_counter <= debounce_counter + 1'b1;
                end else begin
                    // Tecla estável
                    valid <= 1'b1;
                    duration_counter <= duration_counter + 1'b1;
                    press_duration <= duration_counter;

                    case (in)
                        4'b0000: out <= 4'h1;
                        4'b0001: out <= 4'h2;
                        4'b0010: out <= 4'h3;
                        4'b0011: out <= 4'hA;
                        4'b0100: out <= 4'h4;
                        4'b0101: out <= 4'h5;
                        4'b0110: out <= 4'h6;
                        4'b0111: out <= 4'hB;
                        4'b1000: out <= 4'h7;
                        4'b1001: out <= 4'h8;
                        4'b1010: out <= 4'h9;
                        4'b1011: out <= 4'hC;
                        4'b1100: out <= 4'hF;
                        4'b1101: out <= 4'h0;
                        4'b1110: out <= 4'hE;
                        4'b1111: 
                        begin
                        	out <= 4'h0; // nada pressionado
                        	valid <= 1'b0; // não gera tecla válida
                        end
                        default: out <= 4'h0;
                    endcase
                end
            end else begin
                // Tecla mudou: reinicia debounce
                in_prev <= in;
                debounce_counter <= 16'd0;
                duration_counter <= 16'd0;
                valid <= 1'b0;
                press_duration <= 16'd0;
            end
        end
    end
endmodule

tb/tb_keys_4x4.v
`timescale 1ns / 1ps

// Declaração do módulo testbench. Um testbench não possui portas de entrada/saída [25-27].
module tb_keys_4x4;

    // Declaração de sinais internos que atuarão como entradas para o DUT (Device Under Test) [2-23, 27-33]
    reg clk;                       // Clock do sistema
    reg rst;                       // Reset síncrono (assumindo ativo alto, conforme keys_4x4.pdf) [1]
    reg [3:0] in;                  // Entrada da tecla (linha/coluna) [1]

    // Declaração de sinais internos que atuarão como saídas do DUT [2-23, 27-33]
    wire [3:0] out;                // Valor decodificado da tecla [1]
    wire valid;                    // Indica se a tecla foi validada (após debounce) [1]
    wire [15:0] press_duration;    // Duração da tecla pressionada [1]

    // Parâmetro local para controle do tempo de simulação do debounce.
    // Este valor NÃO altera o DEBOUNCE_LIMIT interno do módulo keys_4x4.v.
    // Ele define por quanto tempo o testbench mantém um estímulo de tecla para que o debounce do DUT seja concluído.
    localparam SIM_DEBOUNCE_DELAY = 100; // Tempo em ns para simular o período de estabilização do debounce no TB

    // Instanciação do módulo `keys_4x4`, conectando seus pinos aos sinais do testbench [2-11, 13, 14, 17-20, 23, 26-28, 32-45]
    keys_4x4 DUT (
        .clk(clk),
        .rst(rst),
        .in(in),
        .out(out),
        .valid(valid),
        .press_duration(press_duration)
    );

    // Geração do clock: um sinal de clock com período de 10ns (frequência de 100MHz para simulação) [4-6, 9-11, 14, 18-20, 24, 30, 37-41, 43, 44, 46-54]
    always #5 clk = ~clk;

    // Bloco `initial` para aplicar os estímulos e controlar a simulação [4-6, 9-11, 18-20, 24, 27-30, 33, 37-41, 43, 50-59]
    initial begin
        // Geração do arquivo VCD (Value Change Dump) para visualização das formas de onda [2-7, 9-11, 18-20, 24, 39-41, 43, 44, 52-54, 58]
        $dumpfile("../sim/keys_4x4.vcd");
        $dumpvars(0, tb_keys_4x4); // Registra todos os sinais no módulo 'tb_keys_4x4' para o VCD [24]

        // Configura o monitoramento de sinais para imprimir no console a cada alteração [9, 30, 33, 43, 51, 54, 58-74]
        $monitor("Tempo=%0t | rst=%b | in=%b | out=%b | valid=%b | duracao=%0d", $time, rst, in, out, valid, press_duration);
        $display("------------------------------------------------------------------");
        $display("Iniciando simulação do teclado 4x4...");
        $display("NOTA: Para simulação rápida, o parâmetro DEBOUNCE_LIMIT no keys_4x4.v deve ser ajustado para um valor pequeno (ex: 10).");
        $display("------------------------------------------------------------------");

        // Inicialização de sinais de controle e entrada [4, 5, 9-11, 19, 30, 38, 39, 43, 50-54, 58, 59, 74, 75]
        clk = 0;
        rst = 1;      // Inicia em reset (ativo alto)
        in = 4'b1111; // Assumindo 4'b1111 como "nenhuma tecla pressionada"

        // Pulso de reset: mantém reset ativo por 10ns, depois desativa [4, 5, 9-11, 19, 29, 30, 37-39, 43, 50-54, 58, 59, 74, 75]
        #10;
        rst = 0;      // Libera o reset
        $display("Reset liberado. Teclado inicializado.");
        #20; // Aguarda 2 ciclos de clock para estabilização

        // --- Teste 1: Pressionar tecla '1' (entrada 4'b0000, saída esperada 4'h1) ---
        $display("--- Teste 1: Pressionando Tecla '1' (entrada 4'b0000) ---");
        in = 4'b0000;
        #SIM_DEBOUNCE_DELAY; // Aguarda o período simulado de debounce no TB
        $display("Tecla '1' estabilizada. Valid=1 e duração aumentando devem ser observados.");
        #200; // Mantém a tecla pressionada para observar a duração

        // --- Teste 2: Liberar tecla '1' (voltar para "nenhuma tecla pressionada" 4'b1111) ---
        $display("--- Teste 2: Liberando Tecla '1' ---");
        in = 4'b1111; // Retorna ao estado de nenhuma tecla
        #SIM_DEBOUNCE_DELAY; // Aguarda o período simulado de debounce de liberação
        $display("Tecla '1' liberada. Valid=0 e duração=0 devem ser observados.");
        #100; // Aguarda estabilização

        // --- Teste 3: Pressionar tecla 'A' (entrada 4'b0011, saída esperada 4'hA) ---
        $display("--- Teste 3: Pressionando Tecla 'A' (entrada 4'b0011) ---");
        in = 4'b0011;
        #SIM_DEBOUNCE_DELAY; // Aguarda o debounce
        $display("Tecla 'A' estabilizada. Valid=1 e duração aumentando devem ser observados.");
        #200; // Mantém a tecla pressionada

        // --- Teste 4: Pressionar tecla 'F' (entrada 4'b1100, saída esperada 4'hF) enquanto 'A' está pressionada (simulando múltiplas teclas, mas o módulo lida com uma por vez) ---
        $display("--- Teste 4: Pressionando Tecla 'F' (entrada 4'b1100) - Simulação de mudança de tecla ---");
        in = 4'b1100;
        #SIM_DEBOUNCE_DELAY; // Aguarda o debounce da nova tecla
        $display("Tecla 'F' estabilizada. Valid=1 e duração aumentando devem ser observados.");
        #150; // Mantém a tecla pressionada

        // --- Teste 5: Liberar tecla 'F' ---
        $display("--- Teste 5: Liberando Tecla 'F' ---");
        in = 4'b1111;
        #SIM_DEBOUNCE_DELAY;
        $display("Tecla 'F' liberada.");
        #100;

        // --- Finalizar simulação ---
        $display("------------------------------------------------------------------");
        $display("Simulação concluída. Verifique 'keys_4x4.vcd' para as formas de onda.");
        #10; // Pequeno atraso final para capturar últimos eventos no VCD
        $finish;    // Termina a simulação [4, 11, 24, 30, 33, 38, 39, 50, 55, 64, 69, 71, 72, 75-87]
    end

endmodule

sim/keys_4x4.vcd
$date
	Mon Sep  8 20:47:40 2025
$end
$version
	Icarus Verilog
$end
$timescale
	1ps
$end
$scope module tb_keys_4x4 $end
$var wire 1 ! valid $end
$var wire 16 " press_duration [15:0] $end
$var wire 4 # out [3:0] $end
$var parameter 32 $ SIM_DEBOUNCE_DELAY $end
$var reg 1 % clk $end
$var reg 4 & in [3:0] $end
$var reg 1 ' rst $end
$scope module DUT $end
$var wire 1 % clk $end
$var wire 4 ( in [3:0] $end
$var wire 1 ' rst $end
$var parameter 18 ) DEBOUNCE_LIMIT $end
$var reg 16 * debounce_counter [15:0] $end
$var reg 16 + duration_counter [15:0] $end
$var reg 4 , in_prev [3:0] $end
$var reg 4 - out [3:0] $end
$var reg 16 . press_duration [15:0] $end
$var reg 1 ! valid $end
$upscope $end
$upscope $end
$enddefinitions $end
$comment Show the parameter values. $end
$dumpall
b111101000010010000 )
b1100100 $
$end
#0
$dumpvars
bx .
bx -
bx ,
bx +
bx *
b1111 (
1'
b1111 &
0%
bx #
bx "
x!
$end
#5000
b1111 ,
b0 "
b0 .
b0 +
b0 *
0!
b0 #
b0 -
1%
#10000
0%
0'
#15000
b1 *
1%
#20000
0%
#25000
b10 *
1%
#30000
0%
b0 &
b0 (
#35000
b0 *
b0 ,
1%
#40000
0%
#45000
b1 *
1%
#50000
0%
#55000
b10 *
1%
#60000
0%
#65000
b11 *
1%
#70000
0%
#75000
b100 *
1%
#80000
0%
#85000
b101 *
1%
#90000
0%
#95000
b110 *
1%
#100000
0%
#105000
b111 *
1%
#110000
0%
#115000
b1000 *
1%
#120000
0%
#125000
b1001 *
1%
#130000
0%
#135000
b1010 *
1%
#140000
0%
#145000
b1011 *
1%
#150000
0%
#155000
b1100 *
1%
#160000
0%
#165000
b1101 *
1%
#170000
0%
#175000
b1110 *
1%
#180000
0%
#185000
b1111 *
1%
#190000
0%
#195000
b10000 *
1%
#200000
0%
#205000
b10001 *
1%
#210000
0%
#215000
b10010 *
1%
#220000
0%
#225000
b10011 *
1%
#230000
0%
#235000
b10100 *
1%
#240000
0%
#245000
b10101 *
1%
#250000
0%
#255000
b10110 *
1%
#260000
0%
#265000
b10111 *
1%
#270000
0%
#275000
b11000 *
1%
#280000
0%
#285000
b11001 *
1%
#290000
0%
#295000
b11010 *
1%
#300000
0%
#305000
b11011 *
1%
#310000
0%
#315000
b11100 *
1%
#320000
0%
#325000
b11101 *
1%
#330000
0%
b1111 &
b1111 (
#335000
b0 *
b1111 ,
1%
#340000
0%
#345000
b1 *
1%
#350000
0%
#355000
b10 *
1%
#360000
0%
#365000
b11 *
1%
#370000
0%
#375000
b100 *
1%
#380000
0%
#385000
b101 *
1%
#390000
0%
#395000
b110 *
1%
#400000
0%
#405000
b111 *
1%
#410000
0%
#415000
b1000 *
1%
#420000
0%
#425000
b1001 *
1%
#430000
0%
#435000
b1010 *
1%
#440000
0%
#445000
b1011 *
1%
#450000
0%
#455000
b1100 *
1%
#460000
0%
#465000
b1101 *
1%
#470000
0%
#475000
b1110 *
1%
#480000
0%
#485000
b1111 *
1%
#490000
0%
#495000
b10000 *
1%
#500000
0%
#505000
b10001 *
1%
#510000
0%
#515000
b10010 *
1%
#520000
0%
#525000
b10011 *
1%
#530000
0%
b11 &
b11 (
#535000
b0 *
b11 ,
1%
#540000
0%
#545000
b1 *
1%
#550000
0%
#555000
b10 *
1%
#560000
0%
#565000
b11 *
1%
#570000
0%
#575000
b100 *
1%
#580000
0%
#585000
b101 *
1%
#590000
0%
#595000
b110 *
1%
#600000
0%
#605000
b111 *
1%
#610000
0%
#615000
b1000 *
1%
#620000
0%
#625000
b1001 *
1%
#630000
0%
#635000
b1010 *
1%
#640000
0%
#645000
b1011 *
1%
#650000
0%
#655000
b1100 *
1%
#660000
0%
#665000
b1101 *
1%
#670000
0%
#675000
b1110 *
1%
#680000
0%
#685000
b1111 *
1%
#690000
0%
#695000
b10000 *
1%
#700000
0%
#705000
b10001 *
1%
#710000
0%
#715000
b10010 *
1%
#720000
0%
#725000
b10011 *
1%
#730000
0%
#735000
b10100 *
1%
#740000
0%
#745000
b10101 *
1%
#750000
0%
#755000
b10110 *
1%
#760000
0%
#765000
b10111 *
1%
#770000
0%
#775000
b11000 *
1%
#780000
0%
#785000
b11001 *
1%
#790000
0%
#795000
b11010 *
1%
#800000
0%
#805000
b11011 *
1%
#810000
0%
#815000
b11100 *
1%
#820000
0%
#825000
b11101 *
1%
#830000
0%
b1100 &
b1100 (
#835000
b0 *
b1100 ,
1%
#840000
0%
#845000
b1 *
1%
#850000
0%
#855000
b10 *
1%
#860000
0%
#865000
b11 *
1%
#870000
0%
#875000
b100 *
1%
#880000
0%
#885000
b101 *
1%
#890000
0%
#895000
b110 *
1%
#900000
0%
#905000
b111 *
1%
#910000
0%
#915000
b1000 *
1%
#920000
0%
#925000
b1001 *
1%
#930000
0%
#935000
b1010 *
1%
#940000
0%
#945000
b1011 *
1%
#950000
0%
#955000
b1100 *
1%
#960000
0%
#965000
b1101 *
1%
#970000
0%
#975000
b1110 *
1%
#980000
0%
#985000
b1111 *
1%
#990000
0%
#995000
b10000 *
1%
#1000000
0%
#1005000
b10001 *
1%
#1010000
0%
#1015000
b10010 *
1%
#1020000
0%
#1025000
b10011 *
1%
#1030000
0%
#1035000
b10100 *
1%
#1040000
0%
#1045000
b10101 *
1%
#1050000
0%
#1055000
b10110 *
1%
#1060000
0%
#1065000
b10111 *
1%
#1070000
0%
#1075000
b11000 *
1%
#1080000
0%
b1111 &
b1111 (
#1085000
b0 *
b1111 ,
1%
#1090000
0%
#1095000
b1 *
1%
#1100000
0%
#1105000
b10 *
1%
#1110000
0%
#1115000
b11 *
1%
#1120000
0%
#1125000
b100 *
1%
#1130000
0%
#1135000
b101 *
1%
#1140000
0%
#1145000
b110 *
1%
#1150000
0%
#1155000
b111 *
1%
#1160000
0%
#1165000
b1000 *
1%
#1170000
0%
#1175000
b1001 *
1%
#1180000
0%
#1185000
b1010 *
1%
#1190000
0%
#1195000
b1011 *
1%
#1200000
0%
#1205000
b1100 *
1%
#1210000
0%
#1215000
b1101 *
1%
#1220000
0%
#1225000
b1110 *
1%
#1230000
0%
#1235000
b1111 *
1%
#1240000
0%
#1245000
b10000 *
1%
#1250000
0%
#1255000
b10001 *
1%
#1260000
0%
#1265000
b10010 *
1%
#1270000
0%
#1275000
b10011 *
1%
#1280000
0%
#1285000
b10100 *
1%
