hdl/display7seg_4dig.v
module display7seg_4dig(
    input  wire clk,              // clock do sistema
    input  wire reset,            // reset
    input  wire [15:0] bcd_in,    // 4 dígitos em BCD (cada 4 bits)
    output reg [6:0] seg,         // segmentos a-g (ativo em 0 se catodo comum)
    output reg [3:0] an           // enable de cada dígito (ativo em 0 se catodo comum)
);

    // Registradores internos
    reg [1:0] digit_sel;          // seleciona qual dígito está ativo (0–3)
    reg [3:0] current_digit;      // valor BCD do dígito atual

    // Divisor de clock para multiplexação (~1kHz)
    reg [15:0] clkdiv;
    always @(posedge clk or posedge reset) begin
        if (reset)
            clkdiv <= 0;
        else
            clkdiv <= clkdiv + 1;
    end

    // Seleção de dígito (a cada overflow parcial do divisor)
    always @(posedge clkdiv[15] or posedge reset) begin
        if (reset)
            digit_sel <= 0;
        else
            digit_sel <= digit_sel + 1;
    end

    // Ativa apenas um dígito por vez
    always @(*) begin
        case (digit_sel)
            2'd0: begin an = 4'b1110; current_digit = bcd_in[3:0];   end // dígito menos significativo
            2'd1: begin an = 4'b1101; current_digit = bcd_in[7:4];   end
            2'd2: begin an = 4'b1011; current_digit = bcd_in[11:8];  end
            2'd3: begin an = 4'b0111; current_digit = bcd_in[15:12]; end // dígito mais significativo
            default: begin an = 4'b1111; current_digit = 4'd0; end
        endcase
    end

    // Decodificação BCD → segmentos (a-g)
    always @(*) begin
        case (current_digit)
            4'd0: seg = 7'b1000000;
            4'd1: seg = 7'b1111001;
            4'd2: seg = 7'b0100100;
            4'd3: seg = 7'b0110000;
            4'd4: seg = 7'b0011001;
            4'd5: seg = 7'b0010010;
            4'd6: seg = 7'b0000010;
            4'd7: seg = 7'b1111000;
            4'd8: seg = 7'b0000000;
            4'd9: seg = 7'b0010000;
            default: seg = 7'b1111111; // apagado
        endcase
    end

endmodule

hdl/keys_4x4.v
module keys_4x4(
    input wire clk,                // Clock do sistema
    input wire rst,                // Reset síncrono
    input wire [3:0] in,           // Entrada da tecla (linha/coluna)
    output reg [3:0] out,          // Valor decodificado da tecla
    output reg valid,              // Indica se a tecla foi validada
    output reg [15:0] press_duration // Duração da tecla pressionada
);

    reg [3:0] in_prev;
    reg [15:0] debounce_counter;
    reg [15:0] duration_counter;

    // reduzido para simulação (antes era 250000)
    parameter DEBOUNCE_LIMIT = 18'd10;

    always @(posedge clk) begin
        if (rst) begin
            out <= 4'h0;
            valid <= 1'b0;
            debounce_counter <= 16'd0;
            duration_counter <= 16'd0;
            press_duration <= 16'd0;
            in_prev <= 4'hF;
        end else begin
            if (in == in_prev) begin
                // Incrementa contador de debounce
                if (debounce_counter < DEBOUNCE_LIMIT) begin
                    debounce_counter <= debounce_counter + 1'b1;
                end else begin
                    // Tecla estável
                    valid <= 1'b1;
                    duration_counter <= duration_counter + 1'b1;
                    press_duration <= duration_counter;

                    case (in)
                        4'b0000: out <= 4'h1;
                        4'b0001: out <= 4'h2;
                        4'b0010: out <= 4'h3;
                        4'b0011: out <= 4'hA;
                        4'b0100: out <= 4'h4;
                        4'b0101: out <= 4'h5;
                        4'b0110: out <= 4'h6;
                        4'b0111: out <= 4'hB;
                        4'b1000: out <= 4'h7;
                        4'b1001: out <= 4'h8;
                        4'b1010: out <= 4'h9;
                        4'b1011: out <= 4'hC;
                        4'b1100: out <= 4'hF;
                        4'b1101: out <= 4'h0;
                        4'b1110: out <= 4'hE;
                        4'b1111: 
                        begin
                        	out <= 4'h0; // nada pressionado
                        	valid <= 1'b0; // não gera tecla válida
                        end
                        default: out <= 4'h0;
                    endcase
                end
            end else begin
                // Tecla mudou: reinicia debounce
                in_prev <= in;
                debounce_counter <= 16'd0;
                duration_counter <= 16'd0;
                valid <= 1'b0;
                press_duration <= 16'd0;
            end
        end
    end
endmodule

hdl/top_kd.v
module top_kd(
    input  wire clk,            // clock do sistema
    input  wire rst,            // reset
    input  wire [3:0] key_in,   // entrada do teclado (linha/coluna simulada como 4 bits)
    output wire [6:0] seg,      // segmentos do display
    output wire [3:0] an        // seleção dos dígitos
);

    // sinais do teclado
    wire [3:0] key_value;       // tecla decodificada
    wire valid;                 // tecla válida
    wire [15:0] press_duration; // duração do pressionamento

    reg [15:0] number;          // valor acumulado em 4 dígitos BCD

	// edge detection para valid
	reg valid_prev;
	
    // instância do módulo teclado
    keys_4x4 u_keys (
        .clk(clk),
        .rst(rst),
        .in(key_in),
        .out(key_value),
        .valid(valid),
        .press_duration(press_duration)
    );

    // lógica de acumulação com edge detection
    always @(posedge clk or posedge rst) begin
        if (rst) begin
            number <= 16'h0000;
    		valid_prev <= 1'b0;        
        end else begin
        	valid_prev <= valid;
        	// só acumula quando valid sobe de 0 para 1 - detecta borda de subida de valid
        	if (valid & ~valid_prev) begin
        	    if (key_value == 4'hD) begin
        	    	// clear (tecla D)
        	    	number <= 16'h0000;
        	    end else begin
            		// desloca 3 dígitos para a esquerda e insere novo na posição unidades
            		number <= {number[11:0], key_value};
            	end
            end
        end
    end

    // Instância do display
    display7seg_4dig u_disp (
        .clk(clk),
        .reset(rst),
        .bcd_in(number),
        .seg(seg),
        .an(an)
    );

endmodule

tb/tb_top_kd.v
`timescale 1ns/1ps

module tb_top_kd;

    reg clk;
    reg rst;
    reg [3:0] key_in;
    wire [6:0] seg;
    wire [3:0] an;

    // Instância do DUT
    top_kd dut (
        .clk(clk),
        .rst(rst),
        .key_in(key_in),
        .seg(seg),
        .an(an)
    );

    // Clock 50 MHz
    initial begin
        clk = 0;
        forever #10 clk = ~clk; // período 20ns
    end

    // Estímulos
    initial begin
        $dumpfile("sim/top_kd_simulation.vcd");
        $dumpvars(0, tb_top_kd);

        // Reset inicial
        rst = 1;
        key_in = 4'b1111; // nenhuma tecla
        #100;
        rst = 0;

        // Pressiona tecla "3"
        $display(">>> Pressionando tecla 3");
        key_in = 4'b0010;  // tecla "3"
        #2000;             
        key_in = 4'b1111;  // solta tecla
        #2000;

        // Pressiona tecla "0"
        $display(">>> Pressionando tecla 0");
        key_in = 4'b1101;  // tecla "0"
        #2000;
        key_in = 4'b1111;
        #2000;

        // Finaliza
        $display(">>> Simulação finalizada.");
        #1000;
        $finish;
    end

    // Monitoramento
    initial begin
        $monitor("T=%0t | key_in=%b | seg=%b | an=%b | number=%h",
                  $time, key_in, seg, an, dut.number);
    end

endmodule

sim/top_kd_simulation.vcd
$date
	Tue Sep  9 08:27:56 2025
$end
$version
	Icarus Verilog
$end
$timescale
	1ps
$end
$scope module tb_top_kd $end
$var wire 7 ! seg [6:0] $end
$var wire 4 " an [3:0] $end
$var reg 1 # clk $end
$var reg 4 $ key_in [3:0] $end
$var reg 1 % rst $end
$scope module dut $end
$var wire 1 # clk $end
$var wire 4 & key_in [3:0] $end
$var wire 1 % rst $end
$var wire 1 ' valid $end
$var wire 7 ( seg [6:0] $end
$var wire 16 ) press_duration [15:0] $end
$var wire 4 * key_value [3:0] $end
$var wire 4 + an [3:0] $end
$var reg 16 , number [15:0] $end
$var reg 1 - valid_prev $end
$scope module u_disp $end
$var wire 16 . bcd_in [15:0] $end
$var wire 1 # clk $end
$var wire 1 % reset $end
$var reg 4 / an [3:0] $end
$var reg 16 0 clkdiv [15:0] $end
$var reg 4 1 current_digit [3:0] $end
$var reg 2 2 digit_sel [1:0] $end
$var reg 7 3 seg [6:0] $end
$upscope $end
$scope module u_keys $end
$var wire 1 # clk $end
$var wire 4 4 in [3:0] $end
$var wire 1 % rst $end
$var parameter 18 5 DEBOUNCE_LIMIT $end
$var reg 16 6 debounce_counter [15:0] $end
$var reg 16 7 duration_counter [15:0] $end
$var reg 4 8 in_prev [3:0] $end
$var reg 4 9 out [3:0] $end
$var reg 16 : press_duration [15:0] $end
$var reg 1 ' valid $end
$upscope $end
$upscope $end
$upscope $end
$enddefinitions $end
$comment Show the parameter values. $end
$dumpall
b1010 5
$end
#0
$dumpvars
bx :
bx 9
bx 8
bx 7
bx 6
b1111 4
b1000000 3
b0 2
b0 1
b0 0
b1110 /
b0 .
0-
b0 ,
b1110 +
bx *
bx )
b1000000 (
x'
b1111 &
1%
b1111 $
0#
b1110 "
b1000000 !
$end
#10000
b1111 8
b0 )
b0 :
b0 7
b0 6
0'
b0 *
b0 9
1#
#20000
0#
#30000
1#
#40000
0#
#50000
1#
#60000
0#
#70000
1#
#80000
0#
#90000
1#
#100000
0#
b10 $
b10 &
b10 4
0%
#110000
b1 0
b10 8
1#
#120000
0#
#130000
b10 0
b1 6
1#
#140000
0#
#150000
b11 0
b10 6
1#
#160000
0#
#170000
b100 0
b11 6
1#
#180000
0#
#190000
b101 0
b100 6
1#
#200000
0#
#210000
b110 0
b101 6
1#
#220000
0#
#230000
b111 0
b110 6
1#
#240000
0#
#250000
b1000 0
b111 6
1#
#260000
0#
#270000
b1001 0
b1000 6
1#
#280000
0#
#290000
b1010 0
b1001 6
1#
#300000
0#
#310000
b1011 0
b1010 6
1#
#320000
0#
#330000
b1100 0
b11 *
b11 9
b1 7
1'
1#
#340000
0#
#350000
b110000 !
b110000 (
b110000 3
b11 1
b1101 0
b11 ,
b11 .
1-
b1 )
b1 :
b10 7
1#
#360000
0#
#370000
b1110 0
b10 )
b10 :
b11 7
1#
#380000
0#
#390000
b1111 0
b11 )
b11 :
b100 7
1#
#400000
0#
#410000
b10000 0
b100 )
b100 :
b101 7
1#
#420000
0#
#430000
b10001 0
b101 )
b101 :
b110 7
1#
#440000
0#
#450000
b10010 0
b110 )
b110 :
b111 7
1#
#460000
0#
#470000
b10011 0
b111 )
b111 :
b1000 7
1#
#480000
0#
#490000
b10100 0
b1000 )
b1000 :
b1001 7
1#
#500000
0#
#510000
b10101 0
b1001 )
b1001 :
b1010 7
1#
#520000
0#
#530000
b10110 0
b1010 )
b1010 :
b1011 7
1#
#540000
0#
#550000
b10111 0
b1011 )
b1011 :
b1100 7
1#
#560000
0#
#570000
b11000 0
b1100 )
b1100 :
b1101 7
1#
#580000
0#
#590000
b11001 0
b1101 )
b1101 :
b1110 7
1#
#600000
0#
#610000
b11010 0
b1110 )
b1110 :
b1111 7
1#
#620000
0#
#630000
b11011 0
b1111 )
b1111 :
b10000 7
1#
#640000
0#
#650000
b11100 0
b10000 )
b10000 :
b10001 7
1#
#660000
0#
#670000
b11101 0
b10001 )
b10001 :
b10010 7
1#
#680000
0#
#690000
b11110 0
b10010 )
b10010 :
b10011 7
1#
#700000
0#
#710000
b11111 0
b10011 )
b10011 :
b10100 7
1#
#720000
0#
#730000
b100000 0
b10100 )
b10100 :
b10101 7
1#
#740000
0#
#750000
b100001 0
b10101 )
b10101 :
b10110 7
1#
#760000
0#
#770000
b100010 0
b10110 )
b10110 :
b10111 7
1#
#780000
0#
#790000
b100011 0
b10111 )
b10111 :
b11000 7
1#
#800000
0#
#810000
b100100 0
b11000 )
b11000 :
b11001 7
1#
#820000
0#
#830000
b100101 0
b11001 )
b11001 :
b11010 7
1#
#840000
0#
#850000
b100110 0
b11010 )
b11010 :
b11011 7
1#
#860000
0#
#870000
b100111 0
b11011 )
b11011 :
b11100 7
1#
#880000
0#
#890000
b101000 0
b11100 )
b11100 :
b11101 7
1#
#900000
0#
#910000
b101001 0
b11101 )
b11101 :
b11110 7
1#
#920000
0#
#930000
b101010 0
b11110 )
b11110 :
b11111 7
1#
#940000
0#
#950000
b101011 0
b11111 )
b11111 :
b100000 7
1#
#960000
0#
#970000
b101100 0
b100000 )
b100000 :
b100001 7
1#
#980000
0#
#990000
b101101 0
b100001 )
b100001 :
b100010 7
1#
#1000000
0#
#1010000
b101110 0
b100010 )
b100010 :
b100011 7
1#
#1020000
0#
#1030000
b101111 0
b100011 )
b100011 :
b100100 7
1#
#1040000
0#
#1050000
b110000 0
b100100 )
b100100 :
b100101 7
1#
#1060000
0#
#1070000
b110001 0
b100101 )
b100101 :
b100110 7
1#
#1080000
0#
#1090000
b110010 0
b100110 )
b100110 :
b100111 7
1#
#1100000
0#
#1110000
b110011 0
b100111 )
b100111 :
b101000 7
1#
#1120000
0#
#1130000
b110100 0
b101000 )
b101000 :
b101001 7
1#
#1140000
0#
#1150000
b110101 0
b101001 )
b101001 :
b101010 7
1#
#1160000
0#
#1170000
b110110 0
b101010 )
b101010 :
b101011 7
1#
#1180000
0#
#1190000
b110111 0
b101011 )
b101011 :
b101100 7
1#
#1200000
0#
#1210000
b111000 0
b101100 )
b101100 :
b101101 7
1#
#1220000
0#
#1230000
b111001 0
b101101 )
b101101 :
b101110 7
1#
#1240000
0#
#1250000
b111010 0
b101110 )
b101110 :
b101111 7
1#
#1260000
0#
#1270000
b111011 0
b101111 )
b101111 :
b110000 7
1#
#1280000
0#
#1290000
b111100 0
b110000 )
b110000 :
b110001 7
1#
#1300000
0#
#1310000
b111101 0
b110001 )
b110001 :
b110010 7
1#
#1320000
0#
#1330000
b111110 0
b110010 )
b110010 :
b110011 7
1#
#1340000
0#
#1350000
b111111 0
b110011 )
b110011 :
b110100 7
1#
#1360000
0#
#1370000
b1000000 0
b110100 )
b110100 :
b110101 7
1#
#1380000
0#
#1390000
b1000001 0
b110101 )
b110101 :
b110110 7
1#
#1400000
0#
#1410000
b1000010 0
b110110 )
b110110 :
b110111 7
1#
#1420000
0#
#1430000
b1000011 0
b110111 )
b110111 :
b111000 7
1#
#1440000
0#
#1450000
b1000100 0
b111000 )
b111000 :
b111001 7
1#
#1460000
0#
#1470000
b1000101 0
b111001 )
b111001 :
b111010 7
1#
#1480000
0#
#1490000
b1000110 0
b111010 )
b111010 :
b111011 7
1#
#1500000
0#
#1510000
b1000111 0
b111011 )
b111011 :
b111100 7
1#
#1520000
0#
#1530000
b1001000 0
b111100 )
b111100 :
b111101 7
1#
#1540000
0#
#1550000
b1001001 0
b111101 )
b111101 :
b111110 7
1#
#1560000
0#
#1570000
b1001010 0
b111110 )
b111110 :
b111111 7
1#
#1580000
0#
#1590000
b1001011 0
b111111 )
b111111 :
b1000000 7
1#
#1600000
0#
#1610000
b1001100 0
b1000000 )
b1000000 :
b1000001 7
1#
#1620000
0#
#1630000
b1001101 0
b1000001 )
b1000001 :
b1000010 7
1#
#1640000
0#
#1650000
b1001110 0
b1000010 )
b1000010 :
b1000011 7
1#
#1660000
0#
#1670000
b1001111 0
b1000011 )
b1000011 :
b1000100 7
1#
#1680000
0#
#1690000
b1010000 0
b1000100 )
b1000100 :
b1000101 7
1#
#1700000
0#
#1710000
b1010001 0
b1000101 )
b1000101 :
b1000110 7
1#
#1720000
0#
#1730000
b1010010 0
b1000110 )
b1000110 :
b1000111 7
1#
#1740000
0#
#1750000
b1010011 0
b1000111 )
b1000111 :
b1001000 7
1#
#1760000
0#
#1770000
b1010100 0
b1001000 )
b1001000 :
b1001001 7
1#
#1780000
0#
#1790000
b1010101 0
b1001001 )
b1001001 :
b1001010 7
1#
#1800000
0#
#1810000
b1010110 0
b1001010 )
b1001010 :
b1001011 7
1#
#1820000
0#
#1830000
b1010111 0
b1001011 )
b1001011 :
b1001100 7
1#
#1840000
0#
#1850000
b1011000 0
b1001100 )
b1001100 :
b1001101 7
1#
#1860000
0#
#1870000
b1011001 0
b1001101 )
b1001101 :
b1001110 7
1#
#1880000
0#
#1890000
b1011010 0
b1001110 )
b1001110 :
b1001111 7
1#
#1900000
0#
#1910000
b1011011 0
b1001111 )
b1001111 :
b1010000 7
1#
#1920000
0#
#1930000
b1011100 0
b1010000 )
b1010000 :
b1010001 7
1#
#1940000
0#
#1950000
b1011101 0
b1010001 )
b1010001 :
b1010010 7
1#
#1960000
0#
#1970000
b1011110 0
b1010010 )
b1010010 :
b1010011 7
1#
#1980000
0#
#1990000
b1011111 0
b1010011 )
b1010011 :
b1010100 7
1#
#2000000
0#
#2010000
b1100000 0
b1010100 )
b1010100 :
b1010101 7
1#
#2020000
0#
#2030000
b1100001 0
b1010101 )
b1010101 :
b1010110 7
1#
#2040000
0#
#2050000
b1100010 0
b1010110 )
b1010110 :
b1010111 7
1#
#2060000
0#
#2070000
b1100011 0
b1010111 )
b1010111 :
b1011000 7
1#
#2080000
0#
#2090000
b1100100 0
b1011000 )
b1011000 :
b1011001 7
1#
#2100000
0#
b1111 $
b1111 &
b1111 4
#2110000
b1100101 0
b0 )
b0 :
0'
b0 7
b0 6
b1111 8
1#
#2120000
0#
#2130000
0-
b1100110 0
b1 6
1#
#2140000
0#
#2150000
b1100111 0
b10 6
1#
#2160000
0#
#2170000
b1101000 0
b11 6
1#
#2180000
0#
#2190000
b1101001 0
b100 6
1#
#2200000
0#
#2210000
b1101010 0
b101 6
1#
#2220000
0#
#2230000
b1101011 0
b110 6
1#
#2240000
0#
#2250000
b1101100 0
b111 6
1#
#2260000
0#
#2270000
b1101101 0
b1000 6
1#
#2280000
0#
#2290000
b1101110 0
b1001 6
1#
#2300000
0#
#2310000
b1101111 0
b1010 6
1#
#2320000
0#
#2330000
b1110000 0
b0 *
b0 9
b1 7
0'
1#
#2340000
0#
#2350000
b1110001 0
b1 )
b1 :
b10 7
0'
1#
#2360000
0#
#2370000
b1110010 0
b10 )
b10 :
b11 7
0'
1#
#2380000
0#
#2390000
b1110011 0
b11 )
b11 :
b100 7
0'
1#
#2400000
0#
#2410000
b1110100 0
b100 )
b100 :
b101 7
0'
1#
#2420000
0#
#2430000
b1110101 0
b101 )
b101 :
b110 7
0'
1#
#2440000
0#
#2450000
b1110110 0
b110 )
b110 :
b111 7
0'
1#
#2460000
0#
#2470000
b1110111 0
b111 )
b111 :
b1000 7
0'
1#
#2480000
0#
#2490000
b1111000 0
b1000 )
b1000 :
b1001 7
0'
1#
#2500000
0#
#2510000
b1111001 0
b1001 )
b1001 :
b1010 7
0'
1#
#2520000
0#
#2530000
b1111010 0
b1010 )
b1010 :
b1011 7
0'
1#
#2540000
0#
#2550000
b1111011 0
b1011 )
b1011 :
b1100 7
0'
1#
#2560000
0#
#2570000
b1111100 0
b1100 )
b1100 :
b1101 7
0'
1#
#2580000
0#
#2590000
b1111101 0
b1101 )
b1101 :
b1110 7
0'
1#
#2600000
0#
#2610000
b1111110 0
b1110 )
b1110 :
b1111 7
0'
1#
#2620000
0#
#2630000
b1111111 0
b1111 )
b1111 :
b10000 7
0'
1#
#2640000
0#
#2650000
b10000000 0
b10000 )
b10000 :
b10001 7
0'
1#
#2660000
0#
#2670000
b10000001 0
b10001 )
b10001 :
b10010 7
0'
1#
#2680000
0#
#2690000
b10000010 0
b10010 )
b10010 :
b10011 7
0'
1#
#2700000
0#
#2710000
b10000011 0
b10011 )
b10011 :
b10100 7
0'
1#
#2720000
0#
#2730000
b10000100 0
b10100 )
b10100 :
b10101 7
0'
1#
#2740000
0#
#2750000
b10000101 0
b10101 )
b10101 :
b10110 7
0'
1#
#2760000
0#
#2770000
b10000110 0
b10110 )
b10110 :
b10111 7
0'
1#
#2780000
0#
#2790000
b10000111 0
b10111 )
b10111 :
b11000 7
0'
1#
#2800000
0#
#2810000
b10001000 0
b11000 )
b11000 :
b11001 7
0'
1#
#2820000
0#
#2830000
b10001001 0
b11001 )
b11001 :
b11010 7
0'
1#
#2840000
0#
#2850000
b10001010 0
b11010 )
b11010 :
b11011 7
0'
1#
#2860000
0#
#2870000
b10001011 0
b11011 )
b11011 :
b11100 7
0'
1#
#2880000
0#
#2890000
b10001100 0
b11100 )
b11100 :
b11101 7
0'
1#
#2900000
0#
#2910000
b10001101 0
b11101 )
b11101 :
b11110 7
0'
1#
#2920000
0#
#2930000
b10001110 0
b11110 )
b11110 :
b11111 7
0'
1#
#2940000
0#
#2950000
b10001111 0
b11111 )
b11111 :
b100000 7
0'
1#
#2960000
0#
#2970000
b10010000 0
b100000 )
b100000 :
b100001 7
0'
1#
#2980000
0#
#2990000
b10010001 0
b100001 )
b100001 :
b100010 7
0'
1#
#3000000
0#
#3010000
b10010010 0
b100010 )
b100010 :
b100011 7
0'
1#
#3020000
0#
#3030000
b10010011 0
b100011 )
b100011 :
b100100 7
0'
1#
#3040000
0#
#3050000
b10010100 0
b100100 )
b100100 :
b100101 7
0'
1#
#3060000
0#
#3070000
b10010101 0
b100101 )
b100101 :
b100110 7
0'
1#
#3080000
0#
#3090000
b10010110 0
b100110 )
b100110 :
b100111 7
0'
1#
#3100000
0#
#3110000
b10010111 0
b100111 )
b100111 :
b101000 7
0'
1#
#3120000
0#
#3130000
b10011000 0
b101000 )
b101000 :
b101001 7
0'
1#
#3140000
0#
#3150000
b10011001 0
b101001 )
b101001 :
b101010 7
0'
1#
#3160000
0#
#3170000
b10011010 0
b101010 )
b101010 :
b101011 7
0'
1#
#3180000
0#
#3190000
b10011011 0
b101011 )
b101011 :
b101100 7
0'
1#
#3200000
0#
#3210000
b10011100 0
b101100 )
b101100 :
b101101 7
0'
1#
#3220000
0#
#3230000
b10011101 0
b101101 )
b101101 :
b101110 7
0'
1#
#3240000
0#
#3250000
b10011110 0
b101110 )
b101110 :
b101111 7
0'
1#
#3260000
0#
#3270000
b10011111 0
b101111 )
b101111 :
b110000 7
0'
1#
#3280000
0#
#3290000
b10100000 0
b110000 )
b110000 :
b110001 7
0'
1#
#3300000
0#
#3310000
b10100001 0
b110001 )
b110001 :
b110010 7
0'
1#
#3320000
0#
#3330000
b10100010 0
b110010 )
b110010 :
b110011 7
0'
1#
#3340000
0#
#3350000
b10100011 0
b110011 )
b110011 :
b110100 7
0'
1#
#3360000
0#
#3370000
b10100100 0
b110100 )
b110100 :
b110101 7
0'
1#
#3380000
0#
#3390000
b10100101 0
b110101 )
b110101 :
b110110 7
0'
1#
#3400000
0#
#3410000
b10100110 0
b110110 )
b110110 :
b110111 7
0'
1#
#3420000
0#
#3430000
b10100111 0
b110111 )
b110111 :
b111000 7
0'
1#
#3440000
0#
#3450000
b10101000 0
b111000 )
b111000 :
b111001 7
0'
1#
#3460000
0#
#3470000
b10101001 0
b111001 )
b111001 :
b111010 7
0'
1#
#3480000
0#
#3490000
b10101010 0
b111010 )
b111010 :
b111011 7
0'
1#
#3500000
0#
#3510000
b10101011 0
b111011 )
b111011 :
b111100 7
0'
1#
#3520000
0#
#3530000
b10101100 0
b111100 )
b111100 :
b111101 7
0'
1#
#3540000
0#
#3550000
b10101101 0
b111101 )
b111101 :
b111110 7
0'
1#
#3560000
0#
#3570000
b10101110 0
b111110 )
b111110 :
b111111 7
0'
1#
#3580000
0#
#3590000
b10101111 0
b111111 )
b111111 :
b1000000 7
0'
1#
#3600000
0#
#3610000
b10110000 0
b1000000 )
b1000000 :
b1000001 7
0'
1#
#3620000
0#
#3630000
b10110001 0
b1000001 )
b1000001 :
b1000010 7
0'
1#
#3640000
0#
#3650000
b10110010 0
b1000010 )
b1000010 :
b1000011 7
0'
1#
#3660000
0#
#3670000
b10110011 0
b1000011 )
b1000011 :
b1000100 7
0'
1#
#3680000
0#
#3690000
b10110100 0
b1000100 )
b1000100 :
b1000101 7
0'
1#
#3700000
0#
#3710000
b10110101 0
b1000101 )
b1000101 :
b1000110 7
0'
1#
#3720000
0#
#3730000
b10110110 0
b1000110 )
b1000110 :
b1000111 7
0'
1#
#3740000
0#
#3750000
b10110111 0
b1000111 )
b1000111 :
b1001000 7
0'
1#
#3760000
0#
#3770000
b10111000 0
b1001000 )
b1001000 :
b1001001 7
0'
1#
#3780000
0#
#3790000
b10111001 0
b1001001 )
b1001001 :
b1001010 7
0'
1#
#3800000
0#
#3810000
b10111010 0
b1001010 )
b1001010 :
b1001011 7
0'
1#
#3820000
0#
#3830000
b10111011 0
b1001011 )
b1001011 :
b1001100 7
0'
1#
#3840000
0#
#3850000
b10111100 0
b1001100 )
b1001100 :
b1001101 7
0'
1#
#3860000
0#
#3870000
b10111101 0
b1001101 )
b1001101 :
b1001110 7
0'
1#
#3880000
0#
#3890000
b10111110 0
b1001110 )
b1001110 :
b1001111 7
0'
1#
#3900000
0#
#3910000
b10111111 0
b1001111 )
b1001111 :
b1010000 7
0'
1#
#3920000
0#
#3930000
b11000000 0
b1010000 )
b1010000 :
b1010001 7
0'
1#
#3940000
0#
#3950000
b11000001 0
b1010001 )
b1010001 :
b1010010 7
0'
1#
#3960000
0#
#3970000
b11000010 0
b1010010 )
b1010010 :
b1010011 7
0'
1#
#3980000
0#
#3990000
b11000011 0
b1010011 )
b1010011 :
b1010100 7
0'
1#
#4000000
0#
#4010000
b11000100 0
b1010100 )
b1010100 :
b1010101 7
0'
1#
#4020000
0#
#4030000
b11000101 0
b1010101 )
b1010101 :
b1010110 7
0'
1#
#4040000
0#
#4050000
b11000110 0
b1010110 )
b1010110 :
b1010111 7
0'
1#
#4060000
0#
#4070000
b11000111 0
b1010111 )
b1010111 :
b1011000 7
0'
1#
#4080000
0#
#4090000
b11001000 0
b1011000 )
b1011000 :
b1011001 7
0'
1#
#4100000
0#
b1101 $
b1101 &
b1101 4
#4110000
b11001001 0
b0 )
b0 :
b0 7
b0 6
b1101 8
1#
#4120000
0#
#4130000
b11001010 0
b1 6
1#
#4140000
0#
#4150000
b11001011 0
b10 6
1#
#4160000
0#
#4170000
b11001100 0
b11 6
1#
#4180000
0#
#4190000
b11001101 0
b100 6
1#
#4200000
0#
#4210000
b11001110 0
b101 6
1#
#4220000
0#
#4230000
b11001111 0
b110 6
1#
#4240000
0#
#4250000
b11010000 0
b111 6
1#
#4260000
0#
#4270000
b11010001 0
b1000 6
1#
#4280000
0#
#4290000
b11010010 0
b1001 6
1#
#4300000
0#
#4310000
b11010011 0
b1010 6
1#
#4320000
0#
#4330000
b11010100 0
b1 7
1'
1#
#4340000
0#
#4350000
b1000000 !
b1000000 (
b1000000 3
b0 1
b11010101 0
b110000 ,
b110000 .
1-
b1 )
b1 :
b10 7
1#
#4360000
0#
#4370000
b11010110 0
b10 )
b10 :
b11 7
1#
#4380000
0#
#4390000
b11010111 0
b11 )
b11 :
b100 7
1#
#4400000
0#
#4410000
b11011000 0
b100 )
b100 :
b101 7
1#
#4420000
0#
#4430000
b11011001 0
b101 )
b101 :
b110 7
1#
#4440000
0#
#4450000
b11011010 0
b110 )
b110 :
b111 7
1#
#4460000
0#
#4470000
b11011011 0
b111 )
b111 :
b1000 7
1#
#4480000
0#
#4490000
b11011100 0
b1000 )
b1000 :
b1001 7
1#
#4500000
0#
#4510000
b11011101 0
b1001 )
b1001 :
b1010 7
1#
#4520000
0#
#4530000
b11011110 0
b1010 )
b1010 :
b1011 7
1#
#4540000
0#
#4550000
b11011111 0
b1011 )
b1011 :
b1100 7
1#
#4560000
0#
#4570000
b11100000 0
b1100 )
b1100 :
b1101 7
1#
#4580000
0#
#4590000
b11100001 0
b1101 )
b1101 :
b1110 7
1#
#4600000
0#
#4610000
b11100010 0
b1110 )
b1110 :
b1111 7
1#
#4620000
0#
#4630000
b11100011 0
b1111 )
b1111 :
b10000 7
1#
#4640000
0#
#4650000
b11100100 0
b10000 )
b10000 :
b10001 7
1#
#4660000
0#
#4670000
b11100101 0
b10001 )
b10001 :
b10010 7
1#
#4680000
0#
#4690000
b11100110 0
b10010 )
b10010 :
b10011 7
1#
#4700000
0#
#4710000
b11100111 0
b10011 )
b10011 :
b10100 7
1#
#4720000
0#
#4730000
b11101000 0
b10100 )
b10100 :
b10101 7
1#
#4740000
0#
#4750000
b11101001 0
b10101 )
b10101 :
b10110 7
1#
#4760000
0#
#4770000
b11101010 0
b10110 )
b10110 :
b10111 7
1#
#4780000
0#
#4790000
b11101011 0
b10111 )
b10111 :
b11000 7
1#
#4800000
0#
#4810000
b11101100 0
b11000 )
b11000 :
b11001 7
1#
#4820000
0#
#4830000
b11101101 0
b11001 )
b11001 :
b11010 7
1#
#4840000
0#
#4850000
b11101110 0
b11010 )
b11010 :
b11011 7
1#
#4860000
0#
#4870000
b11101111 0
b11011 )
b11011 :
b11100 7
1#
#4880000
0#
#4890000
b11110000 0
b11100 )
b11100 :
b11101 7
1#
#4900000
0#
#4910000
b11110001 0
b11101 )
b11101 :
b11110 7
1#
#4920000
0#
#4930000
b11110010 0
b11110 )
b11110 :
b11111 7
1#
#4940000
0#
#4950000
b11110011 0
b11111 )
b11111 :
b100000 7
1#
#4960000
0#
#4970000
b11110100 0
b100000 )
b100000 :
b100001 7
1#
#4980000
0#
#4990000
b11110101 0
b100001 )
b100001 :
b100010 7
1#
#5000000
0#
#5010000
b11110110 0
b100010 )
b100010 :
b100011 7
1#
#5020000
0#
#5030000
b11110111 0
b100011 )
b100011 :
b100100 7
1#
#5040000
0#
#5050000
b11111000 0
b100100 )
b100100 :
b100101 7
1#
#5060000
0#
#5070000
b11111001 0
b100101 )
b100101 :
b100110 7
1#
#5080000
0#
#5090000
b11111010 0
b100110 )
b100110 :
b100111 7
1#
#5100000
0#
#5110000
b11111011 0
b100111 )
b100111 :
b101000 7
1#
#5120000
0#
#5130000
b11111100 0
b101000 )
b101000 :
b101001 7
1#
#5140000
0#
#5150000
b11111101 0
b101001 )
b101001 :
b101010 7
1#
#5160000
0#
#5170000
b11111110 0
b101010 )
b101010 :
b101011 7
1#
#5180000
0#
#5190000
b11111111 0
b101011 )
b101011 :
b101100 7
1#
#5200000
0#
#5210000
b100000000 0
b101100 )
b101100 :
b101101 7
1#
#5220000
0#
#5230000
b100000001 0
b101101 )
b101101 :
b101110 7
1#
#5240000
0#
#5250000
b100000010 0
b101110 )
b101110 :
b101111 7
1#
#5260000
0#
#5270000
b100000011 0
b101111 )
b101111 :
b110000 7
1#
#5280000
0#
#5290000
b100000100 0
b110000 )
b110000 :
b110001 7
1#
#5300000
0#
#5310000
b100000101 0
b110001 )
b110001 :
b110010 7
1#
#5320000
0#
#5330000
b100000110 0
b110010 )
b110010 :
b110011 7
1#
#5340000
0#
#5350000
b100000111 0
b110011 )
b110011 :
b110100 7
1#
#5360000
0#
#5370000
b100001000 0
b110100 )
b110100 :
b110101 7
1#
#5380000
0#
#5390000
b100001001 0
b110101 )
b110101 :
b110110 7
1#
#5400000
0#
